soft/__init__.py
soft/factory.py
soft/jsonstorage.py
soft/mongodbstorage.py
soft/netcdf.py
soft/rdf.py
soft/sqlitereader.py
soft/storagestrategy.py
soft/version.py
soft/dataspace/__init__.py
soft/dataspace/database.py
soft/dataspace/dataspace.py
soft/dataspace/document.py
soft/dataspace/entitystore.py
soft7_pkg_quaat-0.0.5.dist-info/LICENSE
soft7_pkg_quaat-0.0.5.dist-info/METADATA
soft7_pkg_quaat-0.0.5.dist-info/WHEEL
soft7_pkg_quaat-0.0.5.dist-info/top_level.txt
soft7_pkg_quaat-0.0.5.dist-info/RECORD
